bugs/__init__.py
bugs-0.0.2.dist-info/LICENSE
bugs-0.0.2.dist-info/METADATA
bugs-0.0.2.dist-info/WHEEL
bugs-0.0.2.dist-info/top_level.txt
bugs-0.0.2.dist-info/RECORD
