Metadata-Version: 2.1
Name: bugs
Version: 0.0.2
Summary: Python essential imports.
Home-page: https://github.com/numpde/bugs
Author: RA
Author-email: numpde@null.net
License: UNKNOWN
Keywords: python essentials
Platform: UNKNOWN
Classifier: Programming Language :: Python :: 3
Classifier: License :: OSI Approved :: MIT License
Classifier: Operating System :: OS Independent
Requires-Python: >=3.6
Requires-Dist: pandas
Requires-Dist: plox
Requires-Dist: inclusive
Requires-Dist: tcga
Requires-Dist: more-itertools
